{
  "Id": "N_REFUGEE_CAMP",
  "Title": "Refugee Camp (Quayside Tents)",
  "Options": [
    {
      "Effects": [
        {
          "Op": "addGold",
          "Amount": -1
        },
        {
          "Op": "setFlag",
          "Id": "camp.helped"
        },
        {
          "Op": "advanceTime",
          "Minutes": 60
        }
      ],
      "Label": "Share a little coin for bread (1g).",
      "Id": "O_SHARE_A_LITTLE_COIN_FOR_BREAD_1G"
    },
    {
      "Effects": [
        {
          "Op": "addGold",
          "Amount": 1
        },
        {
          "Op": "setFlag",
          "Id": "camp.traded"
        }
      ],
      "Label": "Trade odd jobs for a hot drink.",
      "Id": "O_TRADE_ODD_JOBS_FOR_A_HOT_DRINK"
    },
    {
      "Effects": [
        {
          "Op": "combat",
          "Id": "ENEMY_WHARF_THUG"
        }
      ],
      "Label": "Spar with the roughs to pass the time.",
      "Id": "O_SPAR_WITH_THE_ROUGHS_TO_PASS_THE_TIME"
    },
    {
      "Id": "O_EAVESDROP",
      "Label": "Eavesdrop on the crowd.",
      "Effects": [
        {
          "Op": "startDialogue",
          "Id": "D_LORE_N_REFUGEE_CAMP"
        }
      ]
    },
    {
      "Id": "O_TALK_CAMP_ELDER",
      "Effects": [
        {
          "Op": "startDialogue",
          "Id": "D_CAMP_ELDER"
        }
      ],
      "Label": "Speak with the camp elder."
    },
    {
      "Id": "O_TALK_REFUGEE_FAMILY",
      "Effects": [
        {
          "Op": "startDialogue",
          "Id": "D_REFUGEE_FAMILY"
        }
      ],
      "Label": "Check on a refugee family."
    }
  ],
  "Exits": [
    {
      "Text": "To Harbor Town Square",
      "To": "N_HARBOR_SQUARE"
    },
    {
      "Text": "To Ropewalk Lane",
      "To": "N_ROPEWALK"
    },
    {
      "Text": "To Shanty Alley",
      "To": "N_SHANTY_ALLEY"
    }
  ],
  "Description": "Canvas lanes, cookfire smoke, and the patience of people with nowhere left to go.",
  "Paragraphs": [
    "Canvas groans and stove-smoke stings. A bell rings somewhere up the quay.",
    "Ropes creak in the wind and tin stoves tick as they cool. Children chalk games in the dust; a bell somewhere upriver counts the day's last bread.",
    "Aid wagons rattle through with thin blankets and thinner mercy. Between tents, a grey-bearded elder keeps a ledger of names that is mostly crossings-out."
  ]
}